gfapy/__init__.py
gfapy/byte_array.py
gfapy/error.py
gfapy/field_array.py
gfapy/gfa.py
gfapy/lastpos.py
gfapy/logger.py
gfapy/numeric_array.py
gfapy/oriented_line.py
gfapy/placeholder.py
gfapy/rgfa.py
gfapy/segment_end.py
gfapy/segment_end_path.py
gfapy/sequence.py
gfapy/symbol_invert.py
gfapy/alignment/__init__.py
gfapy/alignment/alignment.py
gfapy/alignment/cigar.py
gfapy/alignment/placeholder.py
gfapy/alignment/trace.py
gfapy/field/__init__.py
gfapy/field/alignment_gfa1.py
gfapy/field/alignment_gfa2.py
gfapy/field/alignment_list_gfa1.py
gfapy/field/byte_array.py
gfapy/field/char.py
gfapy/field/comment.py
gfapy/field/custom_record_type.py
gfapy/field/field.py
gfapy/field/float.py
gfapy/field/generic.py
gfapy/field/identifier_gfa2.py
gfapy/field/identifier_list_gfa2.py
gfapy/field/integer.py
gfapy/field/json.py
gfapy/field/numeric_array.py
gfapy/field/optional_identifier_gfa2.py
gfapy/field/optional_integer.py
gfapy/field/orientation.py
gfapy/field/oriented_identifier_gfa2.py
gfapy/field/oriented_identifier_list_gfa1.py
gfapy/field/oriented_identifier_list_gfa2.py
gfapy/field/parser.py
gfapy/field/path_name_gfa1.py
gfapy/field/position_gfa1.py
gfapy/field/position_gfa2.py
gfapy/field/segment_name_gfa1.py
gfapy/field/sequence_gfa1.py
gfapy/field/sequence_gfa2.py
gfapy/field/string.py
gfapy/field/validator.py
gfapy/field/writer.py
gfapy/graph_operations/__init__.py
gfapy/graph_operations/artifacts.py
gfapy/graph_operations/copy_number.py
gfapy/graph_operations/graph_operations.py
gfapy/graph_operations/invertible_segments.py
gfapy/graph_operations/linear_paths.py
gfapy/graph_operations/multiplication.py
gfapy/graph_operations/p_bubbles.py
gfapy/graph_operations/redundant_linear_paths.py
gfapy/graph_operations/superfluous_links.py
gfapy/graph_operations/topology.py
gfapy/line/__init__.py
gfapy/line/line.py
gfapy/line/comment/__init__.py
gfapy/line/comment/comment.py
gfapy/line/comment/construction.py
gfapy/line/comment/tags.py
gfapy/line/comment/version_conversion.py
gfapy-1.2.3.dist-info/LICENSE.txt
gfapy-1.2.3.dist-info/METADATA
gfapy-1.2.3.dist-info/WHEEL
gfapy-1.2.3.dist-info/top_level.txt
gfapy-1.2.3.dist-info/RECORD
