Metadata-Version: 2.1
Name: gfapy
Version: 1.2.3
Summary: Library for handling data in the GFA1 and GFA2 formats
Home-page: https://github.com/ggonnella/gfapy
Author: Giorgio Gonnella and others (see CONTRIBUTORS)
Author-email: gonnella@zbh.uni-hamburg.de
License: ISC
Keywords: bioinformatics genomics sequences GFA assembly graphs
Platform: UNKNOWN
Classifier: Development Status :: 5 - Production/Stable
Classifier: Environment :: Console
Classifier: Intended Audience :: Developers
Classifier: Intended Audience :: End Users/Desktop
Classifier: Intended Audience :: Science/Research
Classifier: License :: OSI Approved :: ISC License (ISCL)
Classifier: Operating System :: MacOS :: MacOS X
Classifier: Operating System :: POSIX :: Linux
Classifier: Programming Language :: Python :: 3 :: Only
Classifier: Topic :: Scientific/Engineering :: Bio-Informatics
Classifier: Topic :: Software Development :: Libraries
